palmettobug/Analysis_functions/Analysis.py
palmettobug/Analysis_functions/SpatialANOVA.py
palmettobug/Analysis_functions/SpatialAnalysis.py
palmettobug/Analysis_functions/WholeClassAnalysis.py
palmettobug/Analysis_functions/__init__.py
palmettobug/Analysis_widgets/Analysis_GUI.py
palmettobug/Analysis_widgets/Spatial_GUI.py
palmettobug/Analysis_widgets/__init__.py
palmettobug/Assets/Capture.ico
palmettobug/Assets/Capture.jpg
palmettobug/Assets/Capture.png
palmettobug/Assets/Capture2.png
palmettobug/Assets/Capture3.jpg
palmettobug/Assets/Capture_2.png
palmettobug/Assets/Capture_blank.png
palmettobug/Assets/LICENSE.txt
palmettobug/Assets/Other_License_Details.txt
palmettobug/Assets/ctkThemeBuilderThemes/Anthracite.json
palmettobug/Assets/ctkThemeBuilderThemes/Cobalt.json
palmettobug/Assets/ctkThemeBuilderThemes/GhostTrain.json
palmettobug/Assets/ctkThemeBuilderThemes/Greengage.json
palmettobug/Assets/ctkThemeBuilderThemes/Hades.json
palmettobug/Assets/ctkThemeBuilderThemes/Harlequin.json
palmettobug/Assets/ctkThemeBuilderThemes/License_of_these_themes(MIT)/LICENSE.txt
palmettobug/Assets/ctkThemeBuilderThemes/MoonlitSky.json
palmettobug/Assets/ctkThemeBuilderThemes/NeonBanana.json
palmettobug/Assets/ctkThemeBuilderThemes/NightTrain.json
palmettobug/Assets/ctkThemeBuilderThemes/Oceanix.json
palmettobug/Assets/ctkThemeBuilderThemes/Sweetkind.json
palmettobug/Assets/ctkThemeBuilderThemes/TestCard.json
palmettobug/Assets/theme.txt
palmettobug/Entrypoint/__init__.py
palmettobug/Entrypoint/app_and_entry.py
palmettobug/Entrypoint/bead_norm.py
palmettobug/Executable.py
palmettobug/ImageProcessing/ImageAnalysisClass.py
palmettobug/ImageProcessing/ImageAnalysisWidgets.py
palmettobug/ImageProcessing/__init__.py
palmettobug/Pixel_Classification/Classifiers.py
palmettobug/Pixel_Classification/Classifiers_GUI.py
palmettobug/Pixel_Classification/__init__.py
palmettobug/Pixel_Classification/use_classifiers.py
palmettobug/Pixel_Classification/use_classifiers_GUI.py
palmettobug-0.2.11.dist-info/METADATA
palmettobug-0.2.11.dist-info/WHEEL
palmettobug-0.2.11.dist-info/entry_points.txt
palmettobug-0.2.11.dist-info/licenses/LICENSE.txt
palmettobug-0.2.11.dist-info/RECORD
