Metadata-Version: 2.4
Name: palmettobug
Version: 0.2.11
Summary: A GUI for (imaging) mass cyometry analysis predominantly based on the popular Steinbock and CATALYST image processing and data analysis packages and written in customtkinter.
License: GPL-3.0
License-File: LICENSE.txt
Author: Ben Caiello
Author-email: <caiello@musc.edu>
Requires-Python: >=3.10
Classifier: License :: OSI Approved :: GNU General Public License v3 (GPLv3)
Classifier: Programming Language :: Python :: 3
Classifier: Programming Language :: Python :: 3.10
Classifier: Programming Language :: Python :: 3.11
Classifier: Programming Language :: Python :: 3.12
Classifier: Programming Language :: Python :: 3.13
Classifier: Programming Language :: Python :: 3.14
Provides-Extra: deprecated-extras
Provides-Extra: instanseg
Requires-Dist: Cython (==3.0.12)
Requires-Dist: FlowIO (==1.3.0)
Requires-Dist: HeapDict (==1.0.1)
Requires-Dist: Jinja2 (==3.1.6)
Requires-Dist: MarkupSafe (==3.0.2)
Requires-Dist: PIMS (==0.7)
Requires-Dist: Pint (==0.24.4)
Requires-Dist: PyOpenGL (==3.1.9)
Requires-Dist: PySide6 (==6.4.3)
Requires-Dist: PySide6-Addons (==6.4.3)
Requires-Dist: PySide6-Essentials (==6.4.3)
Requires-Dist: PyYAML (==6.0.2)
Requires-Dist: Pygments (==2.19.1)
Requires-Dist: QtPy (==2.4.3)
Requires-Dist: Send2Trash (==1.8.3)
Requires-Dist: Sphinx (==8.1.3)
Requires-Dist: aiobotocore (==2.21.1)
Requires-Dist: aiohappyeyeballs (==2.6.1)
Requires-Dist: aiohttp (==3.11.16)
Requires-Dist: aioitertools (==0.12.0)
Requires-Dist: aiosignal (==1.3.2)
Requires-Dist: alabaster (==1.0.0)
Requires-Dist: anndata (==0.11.4)
Requires-Dist: annotated-types (==0.7.0)
Requires-Dist: anyio (==4.9.0)
Requires-Dist: app-model (==0.3.1)
Requires-Dist: appdirs (==1.4.4)
Requires-Dist: argon2-cffi (==23.1.0)
Requires-Dist: argon2-cffi-bindings (==21.2.0)
Requires-Dist: array_api_compat (==1.11.2)
Requires-Dist: arrow (==1.3.0)
Requires-Dist: asciitree (==0.3.3)
Requires-Dist: asttokens (==3.0.0)
Requires-Dist: async-lru (==2.0.5)
Requires-Dist: async-timeout (==5.0.1)
Requires-Dist: attrs (==25.3.0)
Requires-Dist: babel (==2.17.0)
Requires-Dist: beautifulsoup4 (==4.13.3)
Requires-Dist: bleach (==6.2.0)
Requires-Dist: botocore (==1.37.1)
Requires-Dist: build (==1.2.2.post1)
Requires-Dist: cachey (==0.2.1)
Requires-Dist: certifi (==2025.1.31)
Requires-Dist: cffi (==1.17.1)
Requires-Dist: charset-normalizer (==3.4.1)
Requires-Dist: click (==8.1.8)
Requires-Dist: cloudpickle (==3.1.1)
Requires-Dist: colorama (==0.4.6)
Requires-Dist: colorcet (==3.1.0)
Requires-Dist: comm (==0.2.2)
Requires-Dist: contourpy (==1.3.1)
Requires-Dist: customtkinter (==5.2.2)
Requires-Dist: cycler (==0.12.1)
Requires-Dist: darkdetect (==0.8.0)
Requires-Dist: dask (==2024.11.2)
Requires-Dist: dask-expr (==1.1.19)
Requires-Dist: dask-image (==2024.5.3)
Requires-Dist: datashader (==0.18.0)
Requires-Dist: dcor (==0.6)
Requires-Dist: debugpy (==1.8.14)
Requires-Dist: decorator (==5.2.1)
Requires-Dist: defusedxml (==0.7.1)
Requires-Dist: distributed (==2024.11.2)
Requires-Dist: docrep (==0.3.2)
Requires-Dist: docstring_parser (==0.16)
Requires-Dist: docutils (==0.21.2)
Requires-Dist: exceptiongroup (==1.2.2)
Requires-Dist: executing (==2.2.0)
Requires-Dist: fasteners (==0.19)
Requires-Dist: fastjsonschema (==2.21.1)
Requires-Dist: fdasrsf (==2.6.1)
Requires-Dist: findiff (==0.12.1)
Requires-Dist: flexcache (==0.3)
Requires-Dist: flexparser (==0.4)
Requires-Dist: flowsom (==0.2.1)
Requires-Dist: fonttools (==4.57.0)
Requires-Dist: fqdn (==1.5.1)
Requires-Dist: freetype-py (==2.5.1)
Requires-Dist: frozenlist (==1.5.0)
Requires-Dist: fsspec (==2025.3.2)
Requires-Dist: geopandas (==1.0.1)
Requires-Dist: h11 (==0.14.0)
Requires-Dist: h5py (==3.13.0)
Requires-Dist: hsluv (==5.0.4)
Requires-Dist: httpcore (==1.0.8)
Requires-Dist: httpx (==0.28.1)
Requires-Dist: idna (==3.10)
Requires-Dist: igraph (==0.11.8)
Requires-Dist: imageio (==2.37.0)
Requires-Dist: imagesize (==1.4.1)
Requires-Dist: importlib_metadata (==8.6.1)
Requires-Dist: in-n-out (==0.2.1)
Requires-Dist: inflect (==7.5.0)
Requires-Dist: instanseg-torch ; extra == "instanseg"
Requires-Dist: ipykernel (==6.29.5)
Requires-Dist: ipython (==8.35.0)
Requires-Dist: isoduration (==20.11.0)
Requires-Dist: jedi (==0.19.2)
Requires-Dist: jmespath (==1.0.1)
Requires-Dist: joblib (==1.4.2)
Requires-Dist: json5 (==0.12.0)
Requires-Dist: jsonpointer (==3.0.0)
Requires-Dist: jsonschema (==4.23.0)
Requires-Dist: jsonschema-specifications (==2024.10.1)
Requires-Dist: jupyter-events (==0.12.0)
Requires-Dist: jupyter-lsp (==2.2.5)
Requires-Dist: jupyter_client (==8.6.3)
Requires-Dist: jupyter_core (==5.7.2)
Requires-Dist: jupyter_server (==2.15.0)
Requires-Dist: jupyter_server_terminals (==0.5.3)
Requires-Dist: jupyterlab (==4.4.0)
Requires-Dist: jupyterlab_pygments (==0.3.0)
Requires-Dist: jupyterlab_server (==2.27.3)
Requires-Dist: kiwisolver (==1.4.8)
Requires-Dist: lazy_loader (==0.4)
Requires-Dist: legacy-api-wrap (==1.4.1)
Requires-Dist: leidenalg (==0.10.2)
Requires-Dist: llvmlite (==0.44.0)
Requires-Dist: locket (==1.0.0)
Requires-Dist: loguru (==0.7.3)
Requires-Dist: lxml (==5.3.2)
Requires-Dist: magicgui (==0.10.0)
Requires-Dist: markdown-it-py (==3.0.0)
Requires-Dist: matplotlib (==3.10.1)
Requires-Dist: matplotlib-inline (==0.1.7)
Requires-Dist: matplotlib-scalebar (==0.9.0)
Requires-Dist: mdurl (==0.1.2)
Requires-Dist: mistune (==3.1.3)
Requires-Dist: more-itertools (==10.6.0)
Requires-Dist: mpmath (==1.3.0)
Requires-Dist: msgpack (==1.1.0)
Requires-Dist: mudata (==0.3.1)
Requires-Dist: multidict (==6.4.3)
Requires-Dist: multimethod (==2.0)
Requires-Dist: multipledispatch (==1.0.0)
Requires-Dist: multiscale_spatial_image (==2.0.2)
Requires-Dist: napari (==0.5.6)
Requires-Dist: napari-console (==0.1.3)
Requires-Dist: napari-plugin-engine (==0.2.0)
Requires-Dist: napari-svg (==0.2.1)
Requires-Dist: natsort (==8.4.0)
Requires-Dist: navis ; extra == "deprecated-extras"
Requires-Dist: nbclient (==0.10.2)
Requires-Dist: nbconvert (==7.16.6)
Requires-Dist: nbformat (==5.10.4)
Requires-Dist: nest-asyncio (==1.6.0)
Requires-Dist: networkx (==3.4.2)
Requires-Dist: notebook_shim (==0.2.4)
Requires-Dist: npe2 (==0.7.8)
Requires-Dist: numba (==0.61.2)
Requires-Dist: numcodecs (==0.13.1)
Requires-Dist: numpy (==1.26.4)
Requires-Dist: numpydoc (==1.8.0)
Requires-Dist: ome-zarr (==0.10.3)
Requires-Dist: omnipath (==1.0.9)
Requires-Dist: opencv-python-headless (==4.11.0.86)
Requires-Dist: overrides (==7.7.0)
Requires-Dist: packaging (==24.2)
Requires-Dist: pandas (==2.2.3)
Requires-Dist: pandocfilters (==1.5.1)
Requires-Dist: param (==2.2.0)
Requires-Dist: parso (==0.8.4)
Requires-Dist: partd (==1.4.2)
Requires-Dist: patsy (==1.0.1)
Requires-Dist: pillow (==11.2.1)
Requires-Dist: platformdirs (==4.3.7)
Requires-Dist: pooch (==1.8.2)
Requires-Dist: prometheus_client (==0.21.1)
Requires-Dist: prompt_toolkit (==3.0.50)
Requires-Dist: propcache (==0.3.1)
Requires-Dist: psutil (==7.0.0)
Requires-Dist: psygnal (==0.12.0)
Requires-Dist: pure_eval (==0.2.3)
Requires-Dist: pyarrow (==19.0.1)
Requires-Dist: pyconify (==0.2.1)
Requires-Dist: pycparser (==2.22)
Requires-Dist: pyct (==0.5.0)
Requires-Dist: pydantic (==2.11.3)
Requires-Dist: pydantic-compat (==0.1.2)
Requires-Dist: pydantic_core (==2.33.1)
Requires-Dist: pynndescent (==0.5.13)
Requires-Dist: pyogrio (==0.10.0)
Requires-Dist: pyparsing (==3.2.3)
Requires-Dist: pyproj (==3.7.1)
Requires-Dist: pyproject_hooks (==1.2.0)
Requires-Dist: python-dateutil (==2.9.0.post0)
Requires-Dist: python-json-logger (==3.3.0)
Requires-Dist: pytz (==2025.2)
Requires-Dist: pyzmq (==26.4.0)
Requires-Dist: qtconsole (==5.6.1)
Requires-Dist: rdata (==0.11.2)
Requires-Dist: readfcs (==2.0.1)
Requires-Dist: referencing (==0.36.2)
Requires-Dist: requests (==2.32.3)
Requires-Dist: rfc3339-validator (==0.1.4)
Requires-Dist: rfc3986-validator (==0.1.1)
Requires-Dist: rich (==14.0.0)
Requires-Dist: rpds-py (==0.24.0)
Requires-Dist: s3fs (==2025.3.2)
Requires-Dist: scanpy (==1.11.1)
Requires-Dist: scikit-datasets (==0.2.4)
Requires-Dist: scikit-fda (==0.10.1)
Requires-Dist: scikit-image (==0.25.2)
Requires-Dist: scikit-learn (==1.5.2)
Requires-Dist: scipy (==1.15.2)
Requires-Dist: seaborn (==0.13.2)
Requires-Dist: session-info2 (==0.1.2)
Requires-Dist: session_info (==1.0.1)
Requires-Dist: shapely (==2.1.0)
Requires-Dist: shellingham (==1.5.4)
Requires-Dist: shiboken6 (==6.4.3)
Requires-Dist: sigfig (==1.3.18)
Requires-Dist: six (==1.17.0)
Requires-Dist: slicerator (==1.1.0)
Requires-Dist: sniffio (==1.3.1)
Requires-Dist: snowballstemmer (==2.2.0)
Requires-Dist: sortedcontainers (==2.4.0)
Requires-Dist: soupsieve (==2.6)
Requires-Dist: spatial_image (==1.2.1)
Requires-Dist: spatialdata (==0.3.0)
Requires-Dist: sphinxcontrib-applehelp (==2.0.0)
Requires-Dist: sphinxcontrib-devhelp (==2.0.0)
Requires-Dist: sphinxcontrib-htmlhelp (==2.1.0)
Requires-Dist: sphinxcontrib-jsmath (==1.0.1)
Requires-Dist: sphinxcontrib-qthelp (==2.0.0)
Requires-Dist: sphinxcontrib-serializinghtml (==2.0.0)
Requires-Dist: squidpy (==1.6.5)
Requires-Dist: stack-data (==0.6.3)
Requires-Dist: statsmodels (==0.14.4)
Requires-Dist: stdlib-list (==0.11.1)
Requires-Dist: superqt (==0.7.3)
Requires-Dist: svg-stack ; extra == "deprecated-extras"
Requires-Dist: sympy (==1.13.1)
Requires-Dist: tabulate (==0.9.0)
Requires-Dist: tblib (==3.1.0)
Requires-Dist: terminado (==0.18.1)
Requires-Dist: texttable (==1.7.0)
Requires-Dist: threadpoolctl (==3.6.0)
Requires-Dist: tifffile (>=2024.2.12)
Requires-Dist: tinycss2 (==1.4.0)
Requires-Dist: tomli (==2.2.1)
Requires-Dist: tomli_w (==1.2.0)
Requires-Dist: toolz (==1.0.0)
Requires-Dist: tornado (==6.4.2)
Requires-Dist: tqdm (==4.67.1)
Requires-Dist: traitlets (==5.14.3)
Requires-Dist: typeguard (==4.4.2)
Requires-Dist: typer (==0.15.2)
Requires-Dist: types-python-dateutil (==2.9.0.20241206)
Requires-Dist: typing-inspection (==0.4.0)
Requires-Dist: typing_extensions (==4.13.2)
Requires-Dist: tzdata (==2025.2)
Requires-Dist: umap-learn (==0.5.7)
Requires-Dist: uri-template (==1.3.0)
Requires-Dist: urllib3 (==2.4.0)
Requires-Dist: validators (==0.34.0)
Requires-Dist: vispy (==0.14.3)
Requires-Dist: wcwidth (==0.2.13)
Requires-Dist: webcolors (==24.11.1)
Requires-Dist: webencodings (==0.5.1)
Requires-Dist: websocket-client (==1.8.0)
Requires-Dist: wrapt (==1.17.2)
Requires-Dist: xarray (==2024.11.0)
Requires-Dist: xarray-dataclasses (==1.9.1)
Requires-Dist: xarray-schema (==0.0.3)
Requires-Dist: xarray-spatial (==0.4.0)
Requires-Dist: yarl (==1.19.0)
Requires-Dist: zarr (==2.18.3)
Requires-Dist: zict (==3.0.0)
Requires-Dist: zipp (==3.21.0)
